README.md
setup.py
mooda_gui/__init__.py
mooda_gui/__main__.py
mooda_gui.egg-info/PKG-INFO
mooda_gui.egg-info/SOURCES.txt
mooda_gui.egg-info/dependency_links.txt
mooda_gui.egg-info/not-zip-safe
mooda_gui.egg-info/requires.txt
mooda_gui.egg-info/top_level.txt
mooda_gui/widgets/__init__.py
mooda_gui/widgets/dropwidget.py
mooda_gui/widgets/egimdownloaderframe.py
mooda_gui/widgets/histoplotwidget.py
mooda_gui/widgets/mainwindow.py
mooda_gui/widgets/plotsplitter.py
mooda_gui/widgets/qcbarplotwidget.py
mooda_gui/widgets/qcplotwidget.py
mooda_gui/widgets/qcwidget.py
mooda_gui/widgets/renamewidget.py
mooda_gui/widgets/resamplewidget.py
mooda_gui/widgets/scattermatrixplotwidget.py
mooda_gui/widgets/slicewidget.py
mooda_gui/widgets/spectrogramplotwidget.py
mooda_gui/widgets/textframe.py
mooda_gui/widgets/tsplotwidget.py